odoo9_addon_runbot_website_display-9.0.1.0.0-py2.7-nspkg.pth
odoo9_addon_runbot_website_display-9.0.1.0.0.dist-info/top_level.txt
odoo9_addon_runbot_website_display-9.0.1.0.0.dist-info/WHEEL
odoo9_addon_runbot_website_display-9.0.1.0.0.dist-info/RECORD
odoo9_addon_runbot_website_display-9.0.1.0.0.dist-info/metadata.json
odoo9_addon_runbot_website_display-9.0.1.0.0.dist-info/DESCRIPTION.rst
odoo9_addon_runbot_website_display-9.0.1.0.0.dist-info/METADATA
odoo9_addon_runbot_website_display-9.0.1.0.0.dist-info/namespace_packages.txt
odoo_addons/runbot_website_display/__openerp__.py
odoo_addons/runbot_website_display/__init__.py
odoo_addons/runbot_website_display/README.rst
odoo_addons/runbot_website_display/models/__init__.py
odoo_addons/runbot_website_display/models/runbot_repo.py
odoo_addons/runbot_website_display/views/runbot_repo.xml
odoo_addons/runbot_website_display/controllers/runbot_controller.py
odoo_addons/runbot_website_display/controllers/__init__.py
odoo_addons/runbot_website_display/static/description/icon.png
